evolvedominion/__init__.py
evolvedominion/params.py
evolvedominion/play.py
evolvedominion/project.py
evolvedominion/types.py
evolvedominion/utils.py
evolvedominion/agents/__init__.py
evolvedominion/agents/agent.py
evolvedominion/agents/player.py
evolvedominion/agents/strategy.py
evolvedominion/algorithm/__init__.py
evolvedominion/algorithm/evolve.py
evolvedominion/algorithm/models.py
evolvedominion/algorithm/tournaments.py
evolvedominion/display/__init__.py
evolvedominion/display/conf.py
evolvedominion/display/echo.py
evolvedominion/display/text.py
evolvedominion/engine/__init__.py
evolvedominion/engine/combinatorics.py
evolvedominion/engine/engine.py
evolvedominion/engine/pieces.py
evolvedominion/engine/session.py
evolvedominion/engine/state.py
evolvedominion-1.0.3.dist-info/LICENSE
evolvedominion-1.0.3.dist-info/METADATA
evolvedominion-1.0.3.dist-info/WHEEL
evolvedominion-1.0.3.dist-info/entry_points.txt
evolvedominion-1.0.3.dist-info/top_level.txt
evolvedominion-1.0.3.dist-info/RECORD
