Metadata-Version: 2.1
Name: evolvedominion
Version: 1.0.3
Summary: A CLI for evolving and playing against strategies for Dominion.
Home-page: https://github.com/arcboundrav/evodom
Author: Sean Griffin
Author-email: sean.griffin@uwaterloo.ca
Keywords: evolution,genetic algorithm,evodom,dominion
Classifier: Programming Language :: Python :: 3
Classifier: License :: OSI Approved :: MIT License
Classifier: Operating System :: OS Independent
Requires-Python: >=3.10
License-File: LICENSE
Requires-Dist: click (>=8)
Requires-Dist: numba (>=0.55)
Requires-Dist: numpy (>=1.21)
Requires-Dist: platformdirs (>=2.5.2)
Provides-Extra: testing
Requires-Dist: pytest (>=7.0) ; extra == 'testing'
